karrio/server/data/__init__.py
karrio/server/data/admin.py
karrio/server/data/apps.py
karrio/server/data/filters.py
karrio/server/data/models.py
karrio/server/data/signals.py
karrio/server/data/tests.py
karrio/server/data/urls.py
karrio/server/data/migrations/0001_initial.py
karrio/server/data/migrations/0002_alter_batchoperation_resource_type_and_more.py
karrio/server/data/migrations/0003_datatemplate_metadata_alter_batchoperation_resources.py
karrio/server/data/migrations/__init__.py
karrio/server/data/resources/__init__.py
karrio/server/data/resources/orders.py
karrio/server/data/resources/shipments.py
karrio/server/data/resources/trackers.py
karrio/server/data/serializers/__init__.py
karrio/server/data/serializers/base.py
karrio/server/data/serializers/batch.py
karrio/server/data/serializers/batch_orders.py
karrio/server/data/serializers/batch_shipments.py
karrio/server/data/serializers/batch_trackers.py
karrio/server/data/serializers/data.py
karrio/server/data/views/__init__.py
karrio/server/data/views/batch.py
karrio/server/data/views/batch_order.py
karrio/server/data/views/batch_shipment.py
karrio/server/data/views/batch_tracking.py
karrio/server/data/views/data.py
karrio/server/events/task_definitions/__init__.py
karrio/server/events/task_definitions/data/__init__.py
karrio/server/events/task_definitions/data/batch.py
karrio/server/events/task_definitions/data/shipments.py
karrio/server/graph/schemas/__init__.py
karrio/server/graph/schemas/data/__init__.py
karrio/server/graph/schemas/data/inputs.py
karrio/server/graph/schemas/data/mutations.py
karrio/server/graph/schemas/data/types.py
karrio/server/settings/data.py
karrio_server_data-2026.1.4.dist-info/METADATA
karrio_server_data-2026.1.4.dist-info/WHEEL
karrio_server_data-2026.1.4.dist-info/top_level.txt
karrio_server_data-2026.1.4.dist-info/RECORD
