Metadata-Version: 2.4
Name: karrio_server_data
Version: 2026.1.4
Summary: Multi-carrier shipping API data import/export module
Author-email: karrio <hello@karrio.io>
License-Expression: LGPL-3.0
Project-URL: Homepage, https://github.com/karrioapi/karrio
Classifier: Programming Language :: Python :: 3
Requires-Python: >=3.11
Requires-Dist: karrio_server_core
Requires-Dist: karrio_server_events
Requires-Dist: karrio_server_manager
Requires-Dist: django-import-export
